jupyter_cgi_theme/__init__.py
jupyter_cgi_theme/_version.py
jupyter_cgi_theme-1.2.0.data/data/share/jupyter/labextensions/jupyter-cgi-theme/build_log.json
jupyter_cgi_theme-1.2.0.data/data/share/jupyter/labextensions/jupyter-cgi-theme/package.json
jupyter_cgi_theme-1.2.0.data/data/share/jupyter/labextensions/jupyter-cgi-theme/static/2714a8345c85e5efab18.png
jupyter_cgi_theme-1.2.0.data/data/share/jupyter/labextensions/jupyter-cgi-theme/static/5ba9f5de2a2d0be07dd0.png
jupyter_cgi_theme-1.2.0.data/data/share/jupyter/labextensions/jupyter-cgi-theme/static/lib_index_js.0b8aed83da0228dee1cd.js
jupyter_cgi_theme-1.2.0.data/data/share/jupyter/labextensions/jupyter-cgi-theme/static/lib_index_js.0b8aed83da0228dee1cd.js.map
jupyter_cgi_theme-1.2.0.data/data/share/jupyter/labextensions/jupyter-cgi-theme/static/remoteEntry.d3377a0bb05e2a979ec0.js
jupyter_cgi_theme-1.2.0.data/data/share/jupyter/labextensions/jupyter-cgi-theme/static/remoteEntry.d3377a0bb05e2a979ec0.js.map
jupyter_cgi_theme-1.2.0.data/data/share/jupyter/labextensions/jupyter-cgi-theme/static/style.js
jupyter_cgi_theme-1.2.0.data/data/share/jupyter/labextensions/jupyter-cgi-theme/themes/jupyter-cgi-theme/index.css
jupyter_cgi_theme-1.2.0.data/data/share/jupyter/labextensions/jupyter-cgi-theme/themes/jupyter-cgi-theme/index.js
jupyter_cgi_theme-1.2.0.data/data/share/jupyter/labextensions/jupyter-cgi-theme/install.json
jupyter_cgi_theme-1.2.0.dist-info/METADATA
jupyter_cgi_theme-1.2.0.dist-info/WHEEL
jupyter_cgi_theme-1.2.0.dist-info/licenses/LICENSE
jupyter_cgi_theme-1.2.0.dist-info/RECORD
