Metadata-Version: 2.4
Name: jupyter_cgi_theme
Version: 1.2.0
Summary: The JupyterLab CGI theme
Project-URL: Homepage, https://github.com/davideCGI/jupyter-cgi-theme
Project-URL: Bug Tracker, https://github.com/davideCGI/jupyter-cgi-theme/issues
Project-URL: Repository, https://github.com/davideCGI/jupyter-cgi-theme.git
Author-email: Davide Giorgiutti <davide.giorgiutti@cgi.com>
License: BSD 3-Clause License
License-File: LICENSE
Keywords: CGI,jupyter,jupyterlab,jupyterlab-extension
Classifier: Framework :: Jupyter
Classifier: Framework :: Jupyter :: JupyterLab
Classifier: Framework :: Jupyter :: JupyterLab :: 4
Classifier: Framework :: Jupyter :: JupyterLab :: Extensions
Classifier: Framework :: Jupyter :: JupyterLab :: Extensions :: Prebuilt
Classifier: Framework :: Jupyter :: JupyterLab :: Extensions :: Themes
Classifier: License :: OSI Approved :: BSD License
Classifier: Programming Language :: Python
Classifier: Programming Language :: Python :: 3
Classifier: Programming Language :: Python :: 3.8
Classifier: Programming Language :: Python :: 3.9
Classifier: Programming Language :: Python :: 3.10
Classifier: Programming Language :: Python :: 3.11
Classifier: Programming Language :: Python :: 3.12
Requires-Python: >=3.8
